.gitignore
LICENSE
MANIFEST.in
README.md
setup.py
Clortho.egg-info/PKG-INFO
Clortho.egg-info/SOURCES.txt
Clortho.egg-info/dependency_links.txt
Clortho.egg-info/requires.txt
Clortho.egg-info/top_level.txt
clortho/__init__.py
clortho/auth.py
clortho/tests/example.py
clortho/tests/test_auth.py
docs/Makefile
docs/auth.rst
docs/conf.py
docs/index.rst
docs/make.bat