Metadata-Version: 1.1
Name: Clortho
Version: 0.0.0
Summary: Web Authentication with SQLAlchemy
Home-page: http://github.com/shopwiki/clortho
Author: Patrick Lawson
Author-email: plawson@shopwiki.com
License: Apache 2
Platform: UNKNOWN
Classifier: Development Status :: 2 - Pre-Alpha
Classifier: Intended Audience :: Developers
Classifier: License :: OSI Approved :: Apache Software License
Classifier: Operating System :: OS Independent
Classifier: Programming Language :: Python
Classifier: Topic :: Database
Classifier: Topic :: Software Development :: Libraries :: Python Modules
